Metadata-Version: 2.1
Name: sorl-wmark
Version: 1.1.1
Summary: Image based watermarks for sorl-thumbnail
Home-page: https://github.com/sandino/sorl-watermark
Author: Luis Nell
Author-email: cooperate@originell.org
License: UNKNOWN
Platform: any
Classifier: Development Status :: 6 - Mature
Classifier: Environment :: Web Environment
Classifier: Framework :: Django
Classifier: Intended Audience :: Developers
Classifier: License :: OSI Approved :: MIT License
Classifier: Operating System :: OS Independent
Classifier: Programming Language :: Python
Classifier: Programming Language :: Python :: 2
Classifier: Programming Language :: Python :: 2.7
Classifier: Programming Language :: Python :: 3
Classifier: Programming Language :: Python :: 3.7
Classifier: Topic :: Internet :: WWW/HTTP :: Dynamic Content
Classifier: Topic :: Multimedia :: Graphics
Requires-Dist: sorl-thumbnail
